gtrain/__init__.py
gtrain/core.py
gtrain/data.py
gtrain/model.py
gtrain/statutils.py
gtrain/utils.py
gtrain-0.4.0.dist-info/METADATA
gtrain-0.4.0.dist-info/RECORD
gtrain-0.4.0.dist-info/WHEEL
gtrain-0.4.0.dist-info/top_level.txt
