Metadata-Version: 2.1
Name: gtrain
Version: 0.4.0
Summary: Abstraction for general models in TensorFlow with implemented train function
Home-page: https://github.com/fantamat/gtrain
Author: Matěj Fanta
Author-email: fantamat93@gmail.com
License: Apache License 2.0
Platform: UNKNOWN
Classifier: Programming Language :: Python :: 3
Classifier: Operating System :: OS Independent
Classifier: Topic :: Software Development :: Libraries :: Python Modules
Classifier: Topic :: Scientific/Engineering
